cddl_gen/VERSION
cddl_gen/__init__.py
cddl_gen/cddl_gen.py
cddl_gen-0.3.1.data/data/lib/cddl-gen/include/cbor_common.h
cddl_gen-0.3.1.data/data/lib/cddl-gen/include/cbor_debug.h
cddl_gen-0.3.1.data/data/lib/cddl-gen/include/cbor_decode.h
cddl_gen-0.3.1.data/data/lib/cddl-gen/include/cbor_encode.h
cddl_gen-0.3.1.data/data/lib/cddl-gen/src/cbor_common.c
cddl_gen-0.3.1.data/data/lib/cddl-gen/src/cbor_decode.c
cddl_gen-0.3.1.data/data/lib/cddl-gen/src/cbor_encode.c
cddl_gen-0.3.1.dist-info/LICENSE
cddl_gen-0.3.1.dist-info/METADATA
cddl_gen-0.3.1.dist-info/WHEEL
cddl_gen-0.3.1.dist-info/entry_points.txt
cddl_gen-0.3.1.dist-info/top_level.txt
cddl_gen-0.3.1.dist-info/RECORD
