Metadata-Version: 2.1
Name: cddl-gen
Version: 0.3.1
Summary: cddl-gen has been renamed to zcbor!
Home-page: https://github.com/NordicSemiconductor/cddl-gen
Author: Nordic Semiconductor ASA
License: Apache Software License
Platform: UNKNOWN
Classifier: Development Status :: 4 - Beta
Classifier: License :: OSI Approved :: Apache Software License
Classifier: Programming Language :: Python :: 3
Classifier: Topic :: Software Development :: Build Tools
Requires-Python: >=3.6
License-File: LICENSE
Requires-Dist: cbor2 (>=5.4.0)
Requires-Dist: pyyaml (~=5.4.1)
Requires-Dist: regex (>=2020.11.13)
Requires-Dist: zcbor
